flexivsimplugin/__init__.py
flexivsimplugin/flexivsimplugin.cpython-311-x86_64-linux-gnu.so
flexivsimplugin-1.1.0.dist-info/METADATA
flexivsimplugin-1.1.0.dist-info/WHEEL
flexivsimplugin-1.1.0.dist-info/top_level.txt
flexivsimplugin-1.1.0.dist-info/RECORD
flexivsimplugin-1.1.0.dist-info/licenses/LICENSE
