Metadata-Version: 2.4
Name: flexivsimplugin
Version: 1.1.0
Summary: Flexiv Simulation Plugin
Author: Flexiv Ltd.
Author-email: business@flexiv.com
License: Apache-2.0
Requires-Python: >=3.8
License-File: LICENSE
Dynamic: author
Dynamic: author-email
Dynamic: description
Dynamic: license
Dynamic: license-file
Dynamic: requires-python
Dynamic: summary
